lc8_download/__init__.py
lc8_download/lc8.py
lc8_download/scripts/__init__.py
lc8_download/scripts/cli.py
lc8_download-0.3.0.dist-info/DESCRIPTION.rst
lc8_download-0.3.0.dist-info/METADATA
lc8_download-0.3.0.dist-info/RECORD
lc8_download-0.3.0.dist-info/WHEEL
lc8_download-0.3.0.dist-info/entry_points.txt
lc8_download-0.3.0.dist-info/metadata.json
lc8_download-0.3.0.dist-info/top_level.txt
