Metadata-Version: 2.0
Name: lc8-download
Version: 0.3.0
Summary: Library to download Landsat imagery from AWS or Google
Home-page: https://github.com/ibamacsr/lc8_download
Author: Wille Marcel
Author-email: wille@wille.blog.br
License: GPLv3+
Keywords: landsat,satellite imagery,gis
Platform: UNKNOWN
Classifier: License :: OSI Approved :: GNU General Public License v3 or later (GPLv3+)
Classifier: Programming Language :: Python :: 2.7
Classifier: Programming Language :: Python :: 3.4
Classifier: Topic :: Scientific/Engineering :: GIS
Classifier: Topic :: Utilities
Requires-Dist: click
Requires-Dist: homura
Requires-Dist: requests
Provides-Extra: test
Requires-Dist: pytest; extra == 'test'
